{
  "$schema": "https://json.schemastore.org/tsconfig",
  "display": "vite + react",
  "compilerOptions": {
    "strict": true,
    "noUncheckedIndexedAccess": true,
    "noImplicitOverride": true,

    "module": "ESNext",
    "moduleResolution": "Bundler",
    "resolveJsonModule": true,
    "verbatimModuleSyntax": true,

    "noEmit": true,

    "target": "ESNext",
    "lib": ["DOM", "DOM.Iterable", "ESNext"],
    "jsx": "react-jsx",

    "esModuleInterop": true,
    "forceConsistentCasingInFileNames": true,
    "isolatedModules": true,
    "incremental": true,

    "skipLibCheck": true,

    "noUnusedLocals": true,
    "noUnusedParameters": true,
    "noFallthroughCasesInSwitch": true
  },
  "exclude": ["node_modules"]
}
